nbagents/__init__.py
nbagents/nbagents.py
nbagents-0.1.1.dist-info/LICENSE
nbagents-0.1.1.dist-info/METADATA
nbagents-0.1.1.dist-info/WHEEL
nbagents-0.1.1.dist-info/RECORD
