Metadata-Version: 2.3
Name: nbagents
Version: 0.1.1
Summary: A nano, minimalistic, and lightweight library for building ReACT-based AI agents that use tools to solve tasks.
Author: NavuluriBalaji
Author-email: navuluribalaji03@gmail.com
Requires-Python: >=3.8,<4.0
Classifier: Programming Language :: Python :: 3
Classifier: Programming Language :: Python :: 3.8
Classifier: Programming Language :: Python :: 3.9
Classifier: Programming Language :: Python :: 3.10
Classifier: Programming Language :: Python :: 3.11
Classifier: Programming Language :: Python :: 3.12
Classifier: Programming Language :: Python :: 3.13
Requires-Dist: aiohttp (>=3.9.0,<4.0.0)
Requires-Dist: requests (>=2.31.0,<3.0.0)
